{
  "ANALYTICS_NOTES": "The site installs Google Tag Manager only. GA4/Google Tag should be configured inside the GTM container to avoid duplicate page_view events.",
  "APP_HOST": "www-prd.etal.solutions",
  "APP_SLUG": "www",
  "DATA_CLASS": "public",
  "DATA_LIFECYCLE": "persistent",
  "DEPLOYMENT_ID": "www-1778610786",
  "DEPLOY_ENV": "prd",
  "ENV_ROOT": "/home/davidomer/code/corp-www/deploy/prd",
  "GA4_MEASUREMENT_ID": "G-B3YZ2HTFTL",
  "GTM_CONTAINER_ID": "GTM-59XLJP3Q",
  "LIFECYCLE": "long-lived",
  "LOCAL_DOMAIN": "etal.solutions",
  "LOG_DIR": "/home/davidomer/code/corp-www/deploy/prd/logs",
  "MANAGED_BY": "github-pages",
  "OWNER": "omer",
  "OWNER_ALIAS": "etalsolutions",
  "PAGESPEED_APIKEY": "AIzaSyCiz7ukeHKQyMmf5vQnRaBdFgS2cc1oeEE",
  "PM_STATIC_EXCLUDE_DIRS": "capture",
  "PROJECT_ID": "www-1778610786",
  "REPO_ROOT": "/home/davidomer/code/corp-www",
  "RUNTIME_ADAPTER_CODE": "static-github",
  "SITE_BRAND_NAME": "Et al Solutions LLC",
  "SITE_CONTACT_EMAIL": "info@etalsolutions.tech",
  "SITE_DIR": "/home/davidomer/code/corp-www/deploy/prd/www",
  "SITE_ROOT": "/home/davidomer/code/corp-www/deploy/prd/www",
  "SITE_URL": "https://www-prd.etal.solutions",
  "STACK": "www-prd",
  "URI_SCHEME": "https:"
}
